INSTALL.txt
MANIFEST.in
TODO.txt
gen_random_history.py
mcrepogen.conf.example
setup.py
MCREPOGEN.egg-info/PKG-INFO
MCREPOGEN.egg-info/SOURCES.txt
MCREPOGEN.egg-info/dependency_links.txt
MCREPOGEN.egg-info/requires.txt
MCREPOGEN.egg-info/top_level.txt
doc/user_guide.txt
examples/README.txt
examples/all_files.conf
examples/broad_directories.conf
examples/churn.conf
examples/deep_directories.conf
examples/two_kinds_files.conf
mcrepogen/6of12.txt.gz
mcrepogen/__init__.py
mcrepogen/bzrtreebranch.py
mcrepogen/configobj.py
mcrepogen/editors.py
mcrepogen/mutators.py
mcrepogen/transition.py
mcrepogen/treebranch.py
mcrepogen/version_info.py