Metadata-Version: 1.0
Name: MCREPOGEN
Version: 0.2
Summary: Monte Carlo Repository Generator
Home-page: http://launchpad.net/mcrepogen
Author: Neil Martinsen-Burrell
Author-email: nmb@wartburg.edu
License: UNKNOWN
Download-URL: http://launchpad.net/mcrepogen/+download
Platform: UNKNOWN
Classifier: Development Status :: 3 - Alpha
Classifier: Environment :: Console
Classifier: Intended Audience :: Developers
Classifier: Intended Audience :: Science/Research
Classifier: License :: OSI Approved :: GNU General Public License (GPL)
Classifier: Programming Language :: Python :: 2
Classifier: Topic :: Software Development :: Version Control
